[
    {
        "data": "2kj4h2k3j4hkj23h4kj23h4kj2",
        "comment": "первый",
        "datetime": "2026-07-07 21:47:19"
    },
    {
        "data": "1287o1823918231092o3u1",
        "comment": "второй",
        "datetime": "2026-07-07 21:47:19"
    },
    {
        "data": "10012k0k102k10k201",
        "comment": "три",
        "datetime": "2026-07-07 21:47:19"
    },
    {
        "data": "1010101k02k4i43857nv3i458x9",
        "comment": "лвыоалывоалывалыовалыва",
        "datetime": "2026-07-07 21:47:19"
    }
]